Error Resilient RISCV CPU/src/rtl/bch_ecc.v
`timescale 1ns/1ps

module bch_encoder_final (
    input  [31:0] data_in,
    output reg [44:0] codeword
);
    integer i;
    reg [43:0] divreg;
    reg [11:0] parity;

    always @(*) begin
        divreg = {data_in, 12'b0};

        for (i = 43; i >= 12; i = i - 1) begin
            if (divreg[i]) begin
                divreg[i]    = 1'b0;
                divreg[i-2]  = divreg[i-2]  ^ 1'b1;
                divreg[i-4]  = divreg[i-4]  ^ 1'b1;
                divreg[i-7]  = divreg[i-7]  ^ 1'b1;
                divreg[i-8]  = divreg[i-8]  ^ 1'b1;
                divreg[i-9]  = divreg[i-9]  ^ 1'b1;
                divreg[i-12] = divreg[i-12] ^ 1'b1;
            end
        end

        parity   = divreg[11:0];
        codeword = {1'b0, data_in, parity};
    end
endmodule

module bch_encoder (
    input  [31:0] data_in,
    output [44:0] encoded_out
);
    bch_encoder_final encoder_i (
        .data_in(data_in),
        .codeword(encoded_out)
    );
endmodule

module bch_decoder_prod (
    input clk,
    input rst,
    input valid_in,
    input [44:0] data_in,
    output reg valid_out,
    output reg [31:0] data_out,
    output reg fatal,
    output reg [44:0] error_mask,
    output reg [5:0] sigma2
);
    function [5:0] gf_mul;
        input [5:0] a, b;
        reg [10:0] p;
        begin
            p = 0;
            if (b[0]) p = p ^ a;
            if (b[1]) p = p ^ (a << 1);
            if (b[2]) p = p ^ (a << 2);
            if (b[3]) p = p ^ (a << 3);
            if (b[4]) p = p ^ (a << 4);
            if (b[5]) p = p ^ (a << 5);

            gf_mul[0] = p[0] ^ p[6];
            gf_mul[1] = p[1] ^ p[6] ^ p[7];
            gf_mul[2] = p[2] ^ p[7] ^ p[8];
            gf_mul[3] = p[3] ^ p[8] ^ p[9];
            gf_mul[4] = p[4] ^ p[9] ^ p[10];
            gf_mul[5] = p[5] ^ p[10];
        end
    endfunction

    function [5:0] gf_inv;
        input [5:0] a;
        begin
            case(a)
                6'd0:  gf_inv = 6'd0;
                6'd1:  gf_inv = 6'd1;
                6'd2:  gf_inv = 6'd33;
                6'd3:  gf_inv = 6'd62;
                6'd4:  gf_inv = 6'd49;
                6'd5:  gf_inv = 6'd43;
                6'd6:  gf_inv = 6'd31;
                6'd7:  gf_inv = 6'd44;
                6'd8:  gf_inv = 6'd57;
                6'd9:  gf_inv = 6'd37;
                6'd10: gf_inv = 6'd52;
                6'd11: gf_inv = 6'd28;
                6'd12: gf_inv = 6'd46;
                6'd13: gf_inv = 6'd40;
                6'd14: gf_inv = 6'd22;
                6'd15: gf_inv = 6'd25;
                6'd16: gf_inv = 6'd61;
                6'd17: gf_inv = 6'd54;
                6'd18: gf_inv = 6'd51;
                6'd19: gf_inv = 6'd39;
                6'd20: gf_inv = 6'd26;
                6'd21: gf_inv = 6'd35;
                6'd22: gf_inv = 6'd14;
                6'd23: gf_inv = 6'd24;
                6'd24: gf_inv = 6'd23;
                6'd25: gf_inv = 6'd15;
                6'd26: gf_inv = 6'd20;
                6'd27: gf_inv = 6'd34;
                6'd28: gf_inv = 6'd11;
                6'd29: gf_inv = 6'd53;
                6'd30: gf_inv = 6'd45;
                6'd31: gf_inv = 6'd6;
                6'd32: gf_inv = 6'd63;
                6'd33: gf_inv = 6'd2;
                6'd34: gf_inv = 6'd27;
                6'd35: gf_inv = 6'd21;
                6'd36: gf_inv = 6'd56;
                6'd37: gf_inv = 6'd9;
                6'd38: gf_inv = 6'd50;
                6'd39: gf_inv = 6'd19;
                6'd40: gf_inv = 6'd13;
                6'd41: gf_inv = 6'd47;
                6'd42: gf_inv = 6'd48;
                6'd43: gf_inv = 6'd5;
                6'd44: gf_inv = 6'd7;
                6'd45: gf_inv = 6'd30;
                6'd46: gf_inv = 6'd12;
                6'd47: gf_inv = 6'd41;
                6'd48: gf_inv = 6'd42;
                6'd49: gf_inv = 6'd4;
                6'd50: gf_inv = 6'd38;
                6'd51: gf_inv = 6'd18;
                6'd52: gf_inv = 6'd10;
                6'd53: gf_inv = 6'd29;
                6'd54: gf_inv = 6'd17;
                6'd55: gf_inv = 6'd60;
                6'd56: gf_inv = 6'd36;
                6'd57: gf_inv = 6'd8;
                6'd58: gf_inv = 6'd59;
                6'd59: gf_inv = 6'd58;
                6'd60: gf_inv = 6'd55;
                6'd61: gf_inv = 6'd16;
                6'd62: gf_inv = 6'd3;
                6'd63: gf_inv = 6'd32;
                default: gf_inv = 6'd0;
            endcase
        end
    endfunction

    function [5:0] alpha_b;
        input [6:0] e;
        begin
            case(e)
                7'd0:  alpha_b = 6'd1;
                7'd1:  alpha_b = 6'd2;
                7'd2:  alpha_b = 6'd4;
                7'd3:  alpha_b = 6'd8;
                7'd4:  alpha_b = 6'd16;
                7'd5:  alpha_b = 6'd32;
                7'd6:  alpha_b = 6'd3;
                7'd7:  alpha_b = 6'd6;
                7'd8:  alpha_b = 6'd12;
                7'd9:  alpha_b = 6'd24;
                7'd10: alpha_b = 6'd48;
                7'd11: alpha_b = 6'd35;
                7'd12: alpha_b = 6'd5;
                7'd13: alpha_b = 6'd10;
                7'd14: alpha_b = 6'd20;
                7'd15: alpha_b = 6'd40;
                7'd16: alpha_b = 6'd19;
                7'd17: alpha_b = 6'd38;
                7'd18: alpha_b = 6'd15;
                7'd19: alpha_b = 6'd30;
                7'd20: alpha_b = 6'd60;
                7'd21: alpha_b = 6'd59;
                7'd22: alpha_b = 6'd53;
                7'd23: alpha_b = 6'd41;
                7'd24: alpha_b = 6'd17;
                7'd25: alpha_b = 6'd34;
                7'd26: alpha_b = 6'd7;
                7'd27: alpha_b = 6'd14;
                7'd28: alpha_b = 6'd28;
                7'd29: alpha_b = 6'd56;
                7'd30: alpha_b = 6'd51;
                7'd31: alpha_b = 6'd37;
                7'd32: alpha_b = 6'd9;
                7'd33: alpha_b = 6'd18;
                7'd34: alpha_b = 6'd36;
                7'd35: alpha_b = 6'd11;
                7'd36: alpha_b = 6'd22;
                7'd37: alpha_b = 6'd44;
                7'd38: alpha_b = 6'd27;
                7'd39: alpha_b = 6'd54;
                7'd40: alpha_b = 6'd47;
                7'd41: alpha_b = 6'd29;
                7'd42: alpha_b = 6'd58;
                7'd43: alpha_b = 6'd55;
                7'd44: alpha_b = 6'd45;
                7'd45: alpha_b = 6'd25;
                7'd46: alpha_b = 6'd50;
                7'd47: alpha_b = 6'd39;
                7'd48: alpha_b = 6'd13;
                7'd49: alpha_b = 6'd26;
                7'd50: alpha_b = 6'd52;
                7'd51: alpha_b = 6'd43;
                7'd52: alpha_b = 6'd21;
                7'd53: alpha_b = 6'd42;
                7'd54: alpha_b = 6'd23;
                7'd55: alpha_b = 6'd46;
                7'd56: alpha_b = 6'd31;
                7'd57: alpha_b = 6'd62;
                7'd58: alpha_b = 6'd63;
                7'd59: alpha_b = 6'd61;
                7'd60: alpha_b = 6'd57;
                7'd61: alpha_b = 6'd49;
                7'd62: alpha_b = 6'd33;
                default: alpha_b = 6'd0;
            endcase
        end
    endfunction

    function [6:0] mod63_mul3;
        input [5:0] i6;
        reg [7:0] t;
        begin
            t = {2'b00, i6} + {1'b0, i6, 1'b0};
            if (t >= 8'd126)
                mod63_mul3 = t - 8'd126;
            else if (t >= 8'd63)
                mod63_mul3 = t - 8'd63;
            else
                mod63_mul3 = t[6:0];
        end
    endfunction

    function [6:0] mod63_neg;
        input [5:0] k6;
        begin
            if (k6 == 6'd0)
                mod63_neg = 7'd0;
            else
                mod63_neg = 7'd63 - {1'b0, k6};
        end
    endfunction

    function [6:0] mod63_mul2;
        input [6:0] x;
        reg [7:0] t;
        begin
            t = {1'b0, x, 1'b0};
            if (t >= 8'd63)
                mod63_mul2 = t - 8'd63;
            else
                mod63_mul2 = t[6:0];
        end
    endfunction

    reg [5:0] S1, S3;
    reg [44:0] d1;
    reg v1;

    integer i;
    reg [5:0] next_S1, next_S3;
    reg [6:0] exp_s1, exp_s3;

    always @(*) begin
        next_S1 = 6'd0;
        next_S3 = 6'd0;

        for (i = 0; i < 45; i = i + 1) begin
            if (data_in[i]) begin
                exp_s1 = i[6:0];
                exp_s3 = mod63_mul3(i[5:0]);
                next_S1 = next_S1 ^ alpha_b(exp_s1);
                next_S3 = next_S3 ^ alpha_b(exp_s3);
            end
        end
    end

    always @(posedge clk) begin
        if (rst) begin
            S1 <= 6'd0;
            S3 <= 6'd0;
            d1 <= 45'd0;
            v1 <= 1'b0;
        end else begin
            S1 <= next_S1;
            S3 <= next_S3;
            d1 <= data_in;
            v1 <= valid_in;
        end
    end

    reg [5:0] s1, s2;
    reg [44:0] d2;
    reg v2;

    always @(posedge clk) begin
        if (rst) begin
            s1 <= 6'd0;
            s2 <= 6'd0;
            d2 <= 45'd0;
            v2 <= 1'b0;
        end else begin
            s1 <= S1;
            if (S1 == 6'd0)
                s2 <= 6'd0;
            else
                s2 <= gf_mul(gf_mul(gf_mul(S1, S1), S1) ^ S3, gf_inv(S1));
            d2 <= d1;
            v2 <= v1;
        end
    end

    reg [44:0] mask;
    integer k;
    reg [6:0] chien_e1, chien_e2;
    wire [44:0] corrected_cw = d2 ^ mask;

    always @(*) begin
        mask = 45'd0;

        for (k = 0; k < 45; k = k + 1) begin
            chien_e1 = mod63_neg(k[5:0]);
            chien_e2 = mod63_mul2(chien_e1);

            if ((6'd1 ^
                 gf_mul(s1, alpha_b(chien_e1)) ^
                 gf_mul(s2, alpha_b(chien_e2))) == 6'd0)
                mask[k] = 1'b1;
        end
    end

    always @(posedge clk) begin
        if (rst) begin
            valid_out  <= 1'b0;
            data_out   <= 32'd0;
            fatal      <= 1'b0;
            error_mask <= 45'd0;
            sigma2     <= 6'd0;
        end else begin
            valid_out  <= v2;
            data_out   <= corrected_cw[43:12];
            fatal      <= (s1 != 6'd0) && (mask == 45'd0);
            error_mask <= mask;
            sigma2     <= s2;
        end
    end
endmodule

Error Resilient RISCV CPU/src/testbench/tb_2bit_correction.v
`timescale 1ns/1ps

// ============================================================
// Focused testbench: BCH(45,32,t=2) — 2-bit error correction.
//
// Flips bits at positions FAULT_BIT_A and FAULT_BIT_B.
// Key proof signals:
//   S1  != 0  => error detected
//   s2  != 0  => TWO errors (distinguishes from single-bit)
//   error_mask has exactly 2 bits set at the fault positions
//   data_out  == original instruction (both bits corrected)
//   fatal      = 0
//
// Pipeline depth = 3 clock cycles.
// ============================================================

module tb_2bit_correction;

    // ── DUT ports ────────────────────────────────────────────
    reg         clk, rst, valid_in;
    reg  [44:0] data_in;
    wire        valid_out;
    wire        fatal;
    wire [31:0] data_out;
    wire [44:0] error_mask;
    wire [ 5:0] sigma2;

    // ── Instruction and fault positions ──────────────────────
    localparam [31:0] INSTR      = 32'h00208033; // ADD x1,x1,x2
    localparam integer FAULT_BIT_A = 0;           // LSB of codeword (parity)
    localparam integer FAULT_BIT_B = 22;          // data region bit

    // ── Encoder ──────────────────────────────────────────────
    wire [44:0] clean_cw;
    bch_encoder_final enc_i (.data_in(INSTR), .codeword(clean_cw));

    // Flip both fault bits
    wire [44:0] corrupt_cw = clean_cw ^ (45'd1 << FAULT_BIT_A)
                                       ^ (45'd1 << FAULT_BIT_B);

    // ── DUT ──────────────────────────────────────────────────
    bch_decoder_prod uut (
        .clk      (clk),
        .rst      (rst),
        .valid_in (valid_in),
        .data_in  (data_in),
        .valid_out(valid_out),
        .data_out (data_out),
        .fatal    (fatal),
        .error_mask(error_mask),
        .sigma2   (sigma2)
    );

    // ── Clock: 10 ns period ───────────────────────────────────
    initial clk = 0;
    always  #5  clk = ~clk;

    // ── VCD: dump everything ─────────────────────────────────
    initial begin
        $dumpfile("tb_2bit_correction.vcd");
        $dumpvars(0, tb_2bit_correction);
    end

    // ── Main stimulus ─────────────────────────────────────────
    initial begin
        rst = 1; valid_in = 0; data_in = 45'd0;

        $display("============================================================");
        $display("  BCH(45,32,t=2)  Decode-Stage 2-Bit Error Correction Demo  ");
        $display("============================================================");
        $display("  Instruction : ADD x1,x1,x2  (0x%08X)", INSTR);
        $display("  Fault bits  : position %0d AND position %0d", FAULT_BIT_A, FAULT_BIT_B);
        $display("  clean_cw    : 0x%012X", clean_cw);
        $display("  corrupt_cw  : 0x%012X  (bits %0d and %0d flipped)", corrupt_cw, FAULT_BIT_A, FAULT_BIT_B);
        $display("");

        // Hold reset for 4 cycles
        repeat(4) @(posedge clk); #1;
        rst = 0;

        // ── TEST: 2-bit error ─────────────────────────────────
        $display("-- Presenting 2-bit corrupted codeword --");

        @(posedge clk); #1;
        valid_in = 1;
        data_in  = corrupt_cw;
        $display("  Cycle +0 : valid_in=1, data_in=0x%012X", corrupt_cw);

        @(posedge clk); #1;     // Stage 1 — syndrome computed
        valid_in = 0;
        data_in  = 45'd0;
        $display("  Cycle +1 : Stage-1 done | S1=0x%02X S3=0x%02X (non-zero => error detected)", uut.S1, uut.S3);

        @(posedge clk); #1;     // Stage 2 — sigma2 computed
        $display("  Cycle +2 : Stage-2 done | s2=0x%02X (NON-ZERO => TWO-bit error)", uut.s2);

        @(posedge clk); #1;     // Stage 3 — Chien search + output
        $display("  Cycle +3 : OUTPUT:");
        $display("             valid_out  = %b",         valid_out);
        $display("             data_out   = 0x%08X",      data_out);
        $display("             error_mask = 0x%012X",     error_mask);
        $display("             fatal      = %b",          fatal);
        $display("             sigma2     = 0x%02X",      sigma2);
        $display("             bit %0d in mask = %b",     FAULT_BIT_A, error_mask[FAULT_BIT_A]);
        $display("             bit %0d in mask = %b",     FAULT_BIT_B, error_mask[FAULT_BIT_B]);

        if (valid_out && !fatal && data_out == INSTR
            && error_mask[FAULT_BIT_A] && error_mask[FAULT_BIT_B])
            $display("\n>>> RESULT: PASS -- both bit %0d and bit %0d corrected. Original instruction recovered.",
                     FAULT_BIT_A, FAULT_BIT_B);
        else
            $display("\n>>> RESULT: FAIL -- unexpected result.");

        // Idle tail
        repeat(5) @(posedge clk); #1;

        $display("\nWaveform: tb_2bit_correction.vcd");
        $finish;
    end

endmodule

Error Resilient RISCV CPU/tb_2bit_correction.vcd
$date
	Thu May 07 21:23:21 2026
$end
$version
	Icarus Verilog
$end
$timescale
	1ps
$end
$scope module tb_2bit_correction $end
$var wire 45 ! corrupt_cw [44:0] $end
$var wire 1 " valid_out $end
$var wire 6 # sigma2 [5:0] $end
$var wire 1 $ fatal $end
$var wire 45 % error_mask [44:0] $end
$var wire 32 & data_out [31:0] $end
$var wire 45 ' clean_cw [44:0] $end
$var parameter 32 ( FAULT_BIT_A $end
$var parameter 32 ) FAULT_BIT_B $end
$var parameter 32 * INSTR $end
$var reg 1 + clk $end
$var reg 45 , data_in [44:0] $end
$var reg 1 - rst $end
$var reg 1 . valid_in $end
$scope module enc_i $end
$var wire 32 / data_in [31:0] $end
$var reg 45 0 codeword [44:0] $end
$var reg 44 1 divreg [43:0] $end
$var reg 12 2 parity [11:0] $end
$var integer 32 3 i [31:0] $end
$upscope $end
$scope module uut $end
$var wire 1 + clk $end
$var wire 45 4 corrected_cw [44:0] $end
$var wire 45 5 data_in [44:0] $end
$var wire 1 - rst $end
$var wire 1 . valid_in $end
$var reg 6 6 S1 [5:0] $end
$var reg 6 7 S3 [5:0] $end
$var reg 7 8 chien_e1 [6:0] $end
$var reg 7 9 chien_e2 [6:0] $end
$var reg 45 : d1 [44:0] $end
$var reg 45 ; d2 [44:0] $end
$var reg 32 < data_out [31:0] $end
$var reg 45 = error_mask [44:0] $end
$var reg 7 > exp_s1 [6:0] $end
$var reg 7 ? exp_s3 [6:0] $end
$var reg 1 $ fatal $end
$var reg 45 @ mask [44:0] $end
$var reg 6 A next_S1 [5:0] $end
$var reg 6 B next_S3 [5:0] $end
$var reg 6 C s1 [5:0] $end
$var reg 6 D s2 [5:0] $end
$var reg 6 E sigma2 [5:0] $end
$var reg 1 F v1 $end
$var reg 1 G v2 $end
$var reg 1 " valid_out $end
$var integer 32 H i [31:0] $end
$var integer 32 I k [31:0] $end
$scope function alpha_b $end
$var reg 7 J e [6:0] $end
$upscope $end
$scope function gf_inv $end
$var reg 6 K a [5:0] $end
$upscope $end
$scope function gf_mul $end
$var reg 6 L a [5:0] $end
$var reg 6 M b [5:0] $end
$var reg 11 N p [10:0] $end
$upscope $end
$scope function mod63_mul2 $end
$var reg 8 O t [7:0] $end
$var reg 7 P x [6:0] $end
$upscope $end
$scope function mod63_mul3 $end
$var reg 6 Q i6 [5:0] $end
$var reg 8 R t [7:0] $end
$upscope $end
$scope function mod63_neg $end
$var reg 6 S k6 [5:0] $end
$upscope $end
$upscope $end
$upscope $end
$enddefinitions $end
$comment Show the parameter values. $end
$dumpall
b1000001000000000110011 *
b10110 )
b0 (
$end
#0
$dumpvars
bx S
bx R
bx Q
bx P
bx O
bx N
bx M
bx L
bx K
bx J
bx I
b101101 H
xG
xF
bx E
bx D
bx C
b0 B
b0 A
bx @
bx ?
bx >
bx =
bx <
bx ;
bx :
bx 9
bx 8
bx 7
bx 6
b0 5
bx 4
b1011 3
b111101111 2
b111101111 1
b1000001000000000110011000111101111 0
b1000001000000000110011 /
0.
1-
b0 ,
0+
b1000001000000000110011000111101111 '
bx &
bx %
x$
bx #
x"
b1000001000010000110011000111101110 !
$end
#5000
b0 4
b0 N
b0 L
b11011 M
b100110 J
b100110 9
b100110 O
b10011 P
b10011 8
b101100 S
b101101 I
b0 @
0F
b0 :
b0 7
b0 6
0G
b0 ;
b0 D
b0 C
b0 #
b0 E
b0 %
b0 =
0$
b0 &
b0 <
0"
1+
#10000
0+
#15000
1+
#20000
0+
#25000
1+
#30000
0+
#35000
1+
#36000
0-
#40000
0+
#45000
1+
#46000
b1001 B
b110100 A
b100100 J
b100100 ?
b1100011 R
b100001 Q
b100001 >
b101101 H
b1000001000010000110011000111101110 ,
b1000001000010000110011000111101110 5
1.
#50000
0+
#55000
1F
b1000001000010000110011000111101110 :
b1001 7
b110100 6
1+
#56000
b101101 H
b0 B
b0 A
b0 ,
b0 5
0.
#60000
0+
#65000
b1000001000000000110011000111101111 4
b10000000000000000000001 @
b100110 J
b100110 9
b100110 O
b10011 P
b10011 8
b101100 S
b101101 I
0F
b0 :
b0 7
b0 6
1G
b1000001000010000110011000111101110 ;
b110101 D
b110100 C
b110100 K
b1010100111 N
b110101 L
b11011 M
1+
#70000
0+
#75000
b0 4
b0 N
b0 L
b11011 M
b100110 J
b100110 9
b100110 O
b10011 P
b10011 8
b101100 S
b101101 I
b0 @
b110101 #
b110101 E
b10000000000000000000001 %
b10000000000000000000001 =
b1000001000000000110011 &
b1000001000000000110011 <
1"
0G
b0 ;
b0 D
b0 C
1+
#80000
0+
#85000
b0 #
b0 E
b0 %
b0 =
b0 &
b0 <
0"
1+
